odoo/addons/web_view_leaflet_map/README.rst
odoo/addons/web_view_leaflet_map/__init__.py
odoo/addons/web_view_leaflet_map/__manifest__.py
odoo/addons/web_view_leaflet_map/hooks.py
odoo/addons/web_view_leaflet_map/i18n/fr.po
odoo/addons/web_view_leaflet_map/i18n/it.po
odoo/addons/web_view_leaflet_map/i18n/web_view_leaflet_map.pot
odoo/addons/web_view_leaflet_map/models/__init__.py
odoo/addons/web_view_leaflet_map/models/ir_act_window_view.py
odoo/addons/web_view_leaflet_map/models/ir_ui_view.py
odoo/addons/web_view_leaflet_map/models/res_users.py
odoo/addons/web_view_leaflet_map/readme/CONFIGURE.rst
odoo/addons/web_view_leaflet_map/readme/CONTRIBUTORS.rst
odoo/addons/web_view_leaflet_map/readme/DESCRIPTION.rst
odoo/addons/web_view_leaflet_map/readme/DEVELOP.rst
odoo/addons/web_view_leaflet_map/readme/ROADMAP.rst
odoo/addons/web_view_leaflet_map/static/description/icon.png
odoo/addons/web_view_leaflet_map/static/description/index.html
odoo/addons/web_view_leaflet_map/static/description/res_partner_map.png
odoo/addons/web_view_leaflet_map/static/src/css/web_view_leaflet_map.css
odoo/addons/web_view_leaflet_map/static/src/js/view/view_registry.js
odoo/addons/web_view_leaflet_map/static/src/js/view/map/map_renderer.js
odoo/addons/web_view_leaflet_map/static/src/js/view/map/map_view.js
odoo_addon_web_view_leaflet_map-16.0.2.0.0.3.dist-info/METADATA
odoo_addon_web_view_leaflet_map-16.0.2.0.0.3.dist-info/WHEEL
odoo_addon_web_view_leaflet_map-16.0.2.0.0.3.dist-info/top_level.txt
odoo_addon_web_view_leaflet_map-16.0.2.0.0.3.dist-info/RECORD
