Metadata-Version: 2.1
Name: odoo-addon-web_view_leaflet_map
Version: 16.0.2.0.0.3
Summary: Add new 'leaflet_map' view, to display markers.
Home-page: https://github.com/OCA/geospatial
Author: GRAP, Odoo Community Association (OCA)
Author-email: support@odoo-community.org
License: AGPL-3
Classifier: Programming Language :: Python
Classifier: Framework :: Odoo
Classifier: Framework :: Odoo :: 16.0
Classifier: License :: OSI Approved :: GNU Affero General Public License v3
Classifier: Development Status :: 3 - Alpha
Requires-Python: >=3.10
Requires-Dist: odoo-addon-web-leaflet-lib<16.1dev,>=16.0dev
Requires-Dist: odoo<16.1dev,>=16.0a
